LICENSE
MANIFEST.in
README.rst
setup.cfg
setup.py
datatables_optimization/__init__.py
datatables_optimization/mixins.py
datatables_optimization/params.py
django_datatables_optimization.egg-info/PKG-INFO
django_datatables_optimization.egg-info/SOURCES.txt
django_datatables_optimization.egg-info/dependency_links.txt
django_datatables_optimization.egg-info/top_level.txt